{"cameraMode":{"drawMode":0,"name":"Shaded","section":"Shading Mode"},"sceneLighting":true,"audioPlay":false,"sceneViewState":{"showFog":true,"showMaterialUpdate":false,"showSkybox":true,"showFlares":true,"showImageEffects":true,"showParticleSystems":true},"in2DMode":false,"pivot":{"x":-0.970961332321167,"y":0.9141671657562256,"z":1.2115390300750733},"rotation":{"x":-0.16809144616127015,"y":0.7280097007751465,"z":-0.19234921038150788,"w":-0.636198878288269},"size":6.607396125793457,"orthographic":false}